dataroom_client/__init__.py
dataroom_client/client.py
dataroom_client/counter.py
dataroom_client/loader.py
dataroom_client/print_utils.py
dataroom_client-1.0.6.dist-info/METADATA
dataroom_client-1.0.6.dist-info/WHEEL
dataroom_client-1.0.6.dist-info/RECORD
