Metadata-Version: 2.4
Name: dataroom-client
Version: 1.0.6
Summary: A python client to interface with the Dataroom backend API
Author: Ales Kocjancic
Author-email: hi@ales.io
Requires-Python: >=3.10,<4.0
Classifier: Programming Language :: Python :: 3
Classifier: Programming Language :: Python :: 3.10
Classifier: Programming Language :: Python :: 3.11
Classifier: Programming Language :: Python :: 3.12
Classifier: Programming Language :: Python :: 3.13
Classifier: Programming Language :: Python :: 3.14
Requires-Dist: httpx (>=0.28.0,<1)
